CHANGES.rst
CONTRIBUTORS
COPYRIGHT
LICENSE
MANIFEST.in
README.rst
setup.cfg
setup.py
src/who_ldap/__init__.py
src/who_ldap.egg-info/PKG-INFO
src/who_ldap.egg-info/SOURCES.txt
src/who_ldap.egg-info/dependency_links.txt
src/who_ldap.egg-info/not-zip-safe
src/who_ldap.egg-info/requires.txt
src/who_ldap.egg-info/top_level.txt