Metadata-Version: 1.1
Name: who-ldap
Version: 4.0.0
Summary: LDAP plugin for repoze.who
Home-page: https://github.com/m-martinez/who_ldap.git
Author: Marco Martinez
Author-email: UNKNOWN
License: BSD-derived (http://www.repoze.org/LICENSE.txt)
Keywords: ldap web application server wsgi repoze repoze.who
Platform: UNKNOWN
Classifier: Intended Audience :: Developers
Classifier: Natural Language :: English
Classifier: Operating System :: OS Independent
Classifier: Programming Language :: Python
Classifier: Programming Language :: Python :: 2.7
Classifier: Programming Language :: Python :: 3.4
Classifier: Topic :: Internet :: WWW/HTTP :: WSGI :: Middleware
Classifier: Topic :: System :: Systems Administration :: Authentication/Directory :: LDAP
